invenio_unapi/__init__.py
invenio_unapi/config.py
invenio_unapi/version.py
invenio_unapi/views.py
invenio_unapi/templates/unapi/index.xml
invenio_unapi/templates/unapi/index_base.xml
invenio_unapi/translations/invenio.pot
invenio_unapi/translations/de/LC_MESSAGES/messages.mo
invenio_unapi/translations/de/LC_MESSAGES/messages.po
invenio_unapi/translations/es/LC_MESSAGES/messages.mo
invenio_unapi/translations/es/LC_MESSAGES/messages.po
invenio_unapi/translations/fr/LC_MESSAGES/messages.mo
invenio_unapi/translations/fr/LC_MESSAGES/messages.po
invenio_unapi/translations/it/LC_MESSAGES/messages.mo
invenio_unapi/translations/it/LC_MESSAGES/messages.po
invenio_unapi-0.1.1.dist-info/top_level.txt
invenio_unapi-0.1.1.dist-info/METADATA
invenio_unapi-0.1.1.dist-info/DESCRIPTION.rst
invenio_unapi-0.1.1.dist-info/metadata.json
invenio_unapi-0.1.1.dist-info/WHEEL
invenio_unapi-0.1.1.dist-info/RECORD
